jupyterlab_fonts/__init__.py
jupyterlab_fonts/_version.py
jupyterlab_fonts/install.json
jupyterlab_fonts/labextensions/@deathbeds/jupyterlab-font-anonymous-pro/package.json
jupyterlab_fonts/labextensions/@deathbeds/jupyterlab-font-anonymous-pro/static/5df2760a1e9cb54fd5579225878c0ef35effbcd06506780df7a48d779c6a5706.woff2
jupyterlab_fonts/labextensions/@deathbeds/jupyterlab-font-anonymous-pro/static/627.fc9704105e52bb520cdd.js
jupyterlab_fonts/labextensions/@deathbeds/jupyterlab-font-anonymous-pro/static/627.fc9704105e52bb520cdd.js.map
jupyterlab_fonts/labextensions/@deathbeds/jupyterlab-font-anonymous-pro/static/655.cac36cf8f496260b2d30.js
jupyterlab_fonts/labextensions/@deathbeds/jupyterlab-font-anonymous-pro/static/655.cac36cf8f496260b2d30.js.map
jupyterlab_fonts/labextensions/@deathbeds/jupyterlab-font-anonymous-pro/static/900.d765f7dda0d030b64276.js
jupyterlab_fonts/labextensions/@deathbeds/jupyterlab-font-anonymous-pro/static/900.d765f7dda0d030b64276.js.map
jupyterlab_fonts/labextensions/@deathbeds/jupyterlab-font-anonymous-pro/static/91.789856d41dfcfa72590d.js
jupyterlab_fonts/labextensions/@deathbeds/jupyterlab-font-anonymous-pro/static/91.789856d41dfcfa72590d.js.map
jupyterlab_fonts/labextensions/@deathbeds/jupyterlab-font-anonymous-pro/static/c2a8db39a412182257c449b6a331b10132fe030b1a5d6dafb30354687a08074b.woff2
jupyterlab_fonts/labextensions/@deathbeds/jupyterlab-font-anonymous-pro/static/remoteEntry.7dafa2779237f8a139cd.js
jupyterlab_fonts/labextensions/@deathbeds/jupyterlab-font-anonymous-pro/static/remoteEntry.7dafa2779237f8a139cd.js.map
jupyterlab_fonts/labextensions/@deathbeds/jupyterlab-font-anonymous-pro/static/third-party-licenses.json
jupyterlab_fonts/labextensions/@deathbeds/jupyterlab-font-dejavu-sans-mono/package.json
jupyterlab_fonts/labextensions/@deathbeds/jupyterlab-font-dejavu-sans-mono/static/155.32bc345703f1c7368ff2.js
jupyterlab_fonts/labextensions/@deathbeds/jupyterlab-font-dejavu-sans-mono/static/155.32bc345703f1c7368ff2.js.map
jupyterlab_fonts-2.1.1.dist-info/LICENSE
jupyterlab_fonts-2.1.1.dist-info/METADATA
jupyterlab_fonts-2.1.1.dist-info/WHEEL
jupyterlab_fonts-2.1.1.dist-info/top_level.txt
jupyterlab_fonts-2.1.1.dist-info/RECORD
