Metadata-Version: 2.1
Name: jupyterlab-fonts
Version: 2.1.1
Summary: Interactive Typography and Style for JupyterLab
Home-page: https://github.com/deathbeds/jupyterlab-fonts
Author: Dead Pixels Collective
License: BSD-3-Clause
Project-URL: Bug Tracker, https://github.com/deathbeds/jupyterlab-fonts/issues
Project-URL: Source Code, https://github.com/deathbeds/jupyterlab-fonts
Project-URL: Changelog, https://github.com/deathbeds/jupyterlab-fonts/blob/master/CHANGELOG.md
Classifier: Development Status :: 4 - Beta
Classifier: Framework :: Jupyter
Classifier: Framework :: Jupyter :: JupyterLab
Classifier: Framework :: Jupyter :: JupyterLab :: 3
Classifier: Framework :: Jupyter :: JupyterLab :: Extensions
Classifier: Framework :: Jupyter :: JupyterLab :: Extensions :: Prebuilt
Classifier: Intended Audience :: Developers
Classifier: Intended Audience :: Information Technology
Classifier: License :: OSI Approved :: BSD License
Classifier: Programming Language :: Python
Classifier: Programming Language :: Python :: 3 :: Only
Classifier: Programming Language :: Python :: 3.7
Classifier: Programming Language :: Python :: 3.8
Classifier: Programming Language :: Python :: 3.9
Classifier: Programming Language :: Python :: 3.10
Requires-Python: >=3.7
License-File: LICENSE
Requires-Dist: jupyterlab (==3.*)
